ngtonic-1.0.2.dist-info/METADATA
ngtonic-1.0.2.dist-info/WHEEL
ngtonic-1.0.2.dist-info/entry_points.txt
ngtonic-1.0.2.dist-info/licenses/LICENSE
ngtonic/__init__.py
ngtonic/__main__.py
ngtonic/bills.py
ngtonic/importer.py
ngtonic/movements.py
ngtonic/plotter.py
ngtonic/printer.py
ngtonic-1.0.2.dist-info/RECORD
