Metadata-Version: 2.1
Name: ngtonic
Version: 1.0.2
Summary: Personal finances on your terminal
Author-Email: =?utf-8?q?Daniel_Pa=C3=B1eda?= <dpaneda@gmail.com>
License: MIT
Classifier: Intended Audience :: Developers
Classifier: Programming Language :: Python
Classifier: Programming Language :: Python :: 3
Classifier: Programming Language :: Python :: 3 :: Only
Classifier: Programming Language :: Python :: 3.10
Classifier: Programming Language :: Python :: 3.11
Classifier: Programming Language :: Python :: 3.12
Classifier: Programming Language :: Python :: 3.13
Classifier: License :: OSI Approved :: MIT License
Requires-Python: >=3.10
Requires-Dist: matplotlib
Requires-Dist: xlrd
Requires-Dist: unidecode
Requires-Dist: pyyaml>=6.0.2
Requires-Dist: pip>=25.0
Requires-Dist: typer>=0.15.1
Requires-Dist: fastclasses-json>=0.8.0
Requires-Dist: lazy-import>=0.2.2
Requires-Dist: pyqt6>=6.8.1
Requires-Dist: pre-commit>=4.2.0
